{
  "solutions": [
    {
      "name": "2c",
      "solutions": [
        {
          "action_code": "X",
          "frequency": 0.7296079993247986
        },
        {
          "action_code": "R1.8",
          "frequency": 0.06224185600876808
        },
        {
          "action_code": "R3.65",
          "frequency": 0.14678983390331268
        },
        {
          "action_code": "R7.15",
          "frequency": 0.06136031448841095
        },
        {
          "action_code": "RAI",
          "frequency": 0
        }
      ]
    },
    {
      "name": "2d",
      "solutions": [
        {
          "action_code": "X",
          "frequency": 0.7296079993247986
        },
        {
          "action_code": "R1.8",
          "frequency": 0.06224185600876808
        },
        {
          "action_code": "R3.65",
          "frequency": 0.14678983390331268
        },
        {
          "action_code": "R7.15",
          "frequency": 0.06136031448841095
        },
        {
          "action_code": "RAI",
          "frequency": 0
        }
      ]
    },
    {
      "name": "2h",
      "solutions": [
        {
          "action_code": "X",
          "frequency": 0.8610292673110962
        },
        {
          "action_code": "R1.8",
          "frequency": 0.0687820091843605
        },
        {
          "action_code": "R3.65",
          "frequency": 0.03906715288758278
        },
        {
          "action_code": "R7.15",
          "frequency": 0.031121565029025078
        },
        {
          "action_code": "RAI",
          "frequency": 0
        }
      ]
    },
    {
      "name": "2s",
      "solutions": [
        {
          "action_code": "X",
          "frequency": 0.7296079993247986
        },
        {
          "action_code": "R1.8",
          "frequency": 0.06224185600876808
        },
        {
          "action_code": "R3.65",
          "frequency": 0.14678983390331268
        },
        {
          "action_code": "R7.15",
          "frequency": 0.06136031448841095
        },
        {
          "action_code": "RAI",
          "frequency": 0
        }
      ]
    },
    {
      "name": "3c",
      "solutions": [
        {
          "action_code": "X",
          "frequency": 0.7260256409645081
        },
        {
          "action_code": "R1.8",
          "frequency": 0.07268472015857697
        },
        {
          "action_code": "R3.65",
          "frequency": 0.14630688726902008
        },
        {
          "action_code": "R7.15",
          "frequency": 0.05498277395963669
        },
        {
          "action_code": "RAI",
          "frequency": 0
        }
      ]
    },
    {
      "name": "3d",
      "solutions": [
        {
          "action_code": "X",
          "frequency": 0.7260256409645081
        },
        {
          "action_code": "R1.8",
          "frequency": 0.07268472015857697
        },
        {
          "action_code": "R3.65",
          "frequency": 0.14630688726902008
        },
        {
          "action_code": "R7.15",
          "frequency": 0.05498277395963669
        },
        {
          "action_code": "RAI",
          "frequency": 0
        }
      ]
    },
    {
      "name": "3h",
      "solutions": [
        {
          "action_code": "X",
          "frequency": 0.8597946763038635
        },
        {
          "action_code": "R1.8",
          "frequency": 0.06738228350877762
        },
        {
          "action_code": "R3.65",
          "frequency": 0.04617481678724289
        },
        {
          "action_code": "R7.15",
          "frequency": 0.02664819546043873
        },
        {
          "action_code": "RAI",
          "frequency": 0
        }
      ]
    },
    {
      "name": "3s",
      "solutions": [
        {
          "action_code": "X",
          "frequency": 0.7260256409645081
        },
        {
          "action_code": "R1.8",
          "frequency": 0.07268472015857697
        },
        {
          "action_code": "R3.65",
          "frequency": 0.14630688726902008
        },
        {
          "action_code": "R7.15",
          "frequency": 0.05498277395963669
        },
        {
          "action_code": "RAI",
          "frequency": 0
        }
      ]
    },
    {
      "name": "4c",
      "solutions": [
        {
          "action_code": "X",
          "frequency": 0.7476022839546204
        },
        {
          "action_code": "R1.8",
          "frequency": 0.0666326954960823
        },
        {
          "action_code": "R3.65",
          "frequency": 0.13356612622737885
        },
        {
          "action_code": "R7.15",
          "frequency": 0.05219888687133789
        },
        {
          "action_code": "RAI",
          "frequency": 0
        }
      ]
    },
    {
      "name": "4d",
      "solutions": [
        {
          "action_code": "X",
          "frequency": 0.7476022839546204
        },
        {
          "action_code": "R1.8",
          "frequency": 0.0666326954960823
        },
        {
          "action_code": "R3.65",
          "frequency": 0.13356612622737885
        },
        {
          "action_code": "R7.15",
          "frequency": 0.05219888687133789
        },
        {
          "action_code": "RAI",
          "frequency": 0
        }
      ]
    },
    {
      "name": "4h",
      "solutions": [
        {
          "action_code": "X",
          "frequency": 0.8734661936759949
        },
        {
          "action_code": "R1.8",
          "frequency": 0.05330122634768486
        },
        {
          "action_code": "R3.65",
          "frequency": 0.05467440187931061
        },
        {
          "action_code": "R7.15",
          "frequency": 0.018558159470558167
        },
        {
          "action_code": "RAI",
          "frequency": 0
        }
      ]
    },
    {
      "name": "4s",
      "solutions": [
        {
          "action_code": "X",
          "frequency": 0.7476022839546204
        },
        {
          "action_code": "R1.8",
          "frequency": 0.0666326954960823
        },
        {
          "action_code": "R3.65",
          "frequency": 0.13356612622737885
        },
        {
          "action_code": "R7.15",
          "frequency": 0.05219888687133789
        },
        {
          "action_code": "RAI",
          "frequency": 0
        }
      ]
    },
    {
      "name": "5c",
      "solutions": [
        {
          "action_code": "X",
          "frequency": 0.7596458792686462
        },
        {
          "action_code": "R1.8",
          "frequency": 0.06907346099615097
        },
        {
          "action_code": "R3.65",
          "frequency": 0.1552291363477707
        },
        {
          "action_code": "R7.15",
          "frequency": 0.015217401087284088
        },
        {
          "action_code": "RAI",
          "frequency": 0.0008341430220752954
        }
      ]
    },
    {
      "name": "5d",
      "solutions": [
        {
          "action_code": "X",
          "frequency": 0.7596458792686462
        },
        {
          "action_code": "R1.8",
          "frequency": 0.06907346099615097
        },
        {
          "action_code": "R3.65",
          "frequency": 0.1552291363477707
        },
        {
          "action_code": "R7.15",
          "frequency": 0.015217401087284088
        },
        {
          "action_code": "RAI",
          "frequency": 0.0008341430220752954
        }
      ]
    },
    {
      "name": "5s",
      "solutions": [
        {
          "action_code": "X",
          "frequency": 0.7596458792686462
        },
        {
          "action_code": "R1.8",
          "frequency": 0.06907346099615097
        },
        {
          "action_code": "R3.65",
          "frequency": 0.1552291363477707
        },
        {
          "action_code": "R7.15",
          "frequency": 0.015217401087284088
        },
        {
          "action_code": "RAI",
          "frequency": 0.0008341430220752954
        }
      ]
    },
    {
      "name": "6c",
      "solutions": [
        {
          "action_code": "X",
          "frequency": 0.7429257035255432
        },
        {
          "action_code": "R1.8",
          "frequency": 0.08302084356546402
        },
        {
          "action_code": "R3.65",
          "frequency": 0.11888981610536575
        },
        {
          "action_code": "R7.15",
          "frequency": 0.055163610726594925
        },
        {
          "action_code": "RAI",
          "frequency": 0
        }
      ]
    },
    {
      "name": "6d",
      "solutions": [
        {
          "action_code": "X",
          "frequency": 0.7429257035255432
        },
        {
          "action_code": "R1.8",
          "frequency": 0.08302084356546402
        },
        {
          "action_code": "R3.65",
          "frequency": 0.11888981610536575
        },
        {
          "action_code": "R7.15",
          "frequency": 0.055163610726594925
        },
        {
          "action_code": "RAI",
          "frequency": 0
        }
      ]
    },
    {
      "name": "6h",
      "solutions": [
        {
          "action_code": "X",
          "frequency": 0.8741081357002258
        },
        {
          "action_code": "R1.8",
          "frequency": 0.06052485853433609
        },
        {
          "action_code": "R3.65",
          "frequency": 0.05604662373661995
        },
        {
          "action_code": "R7.15",
          "frequency": 0.00932040810585022
        },
        {
          "action_code": "RAI",
          "frequency": 0
        }
      ]
    },
    {
      "name": "6s",
      "solutions": [
        {
          "action_code": "X",
          "frequency": 0.7429257035255432
        },
        {
          "action_code": "R1.8",
          "frequency": 0.08302084356546402
        },
        {
          "action_code": "R3.65",
          "frequency": 0.11888981610536575
        },
        {
          "action_code": "R7.15",
          "frequency": 0.055163610726594925
        },
        {
          "action_code": "RAI",
          "frequency": 0
        }
      ]
    },
    {
      "name": "7c",
      "solutions": [
        {
          "action_code": "X",
          "frequency": 0.7317385077476501
        },
        {
          "action_code": "R1.8",
          "frequency": 0.08065592497587204
        },
        {
          "action_code": "R3.65",
          "frequency": 0.14678187668323517
        },
        {
          "action_code": "R7.15",
          "frequency": 0.04082367196679115
        },
        {
          "action_code": "RAI",
          "frequency": 0
        }
      ]
    },
    {
      "name": "7d",
      "solutions": [
        {
          "action_code": "X",
          "frequency": 0.7317385077476501
        },
        {
          "action_code": "R1.8",
          "frequency": 0.08065592497587204
        },
        {
          "action_code": "R3.65",
          "frequency": 0.14678187668323517
        },
        {
          "action_code": "R7.15",
          "frequency": 0.04082367196679115
        },
        {
          "action_code": "RAI",
          "frequency": 0
        }
      ]
    },
    {
      "name": "7h",
      "solutions": [
        {
          "action_code": "X",
          "frequency": 0.8717290759086609
        },
        {
          "action_code": "R1.8",
          "frequency": 0.0649566799402237
        },
        {
          "action_code": "R3.65",
          "frequency": 0.05714290589094162
        },
        {
          "action_code": "R7.15",
          "frequency": 0.006171338725835085
        },
        {
          "action_code": "RAI",
          "frequency": 0
        }
      ]
    },
    {
      "name": "7s",
      "solutions": [
        {
          "action_code": "X",
          "frequency": 0.7317385077476501
        },
        {
          "action_code": "R1.8",
          "frequency": 0.08065592497587204
        },
        {
          "action_code": "R3.65",
          "frequency": 0.14678187668323517
        },
        {
          "action_code": "R7.15",
          "frequency": 0.04082367196679115
        },
        {
          "action_code": "RAI",
          "frequency": 0
        }
      ]
    },
    {
      "name": "8c",
      "solutions": [
        {
          "action_code": "X",
          "frequency": 0.7440924048423767
        },
        {
          "action_code": "R1.8",
          "frequency": 0.08388570696115494
        },
        {
          "action_code": "R3.65",
          "frequency": 0.1307249814271927
        },
        {
          "action_code": "R7.15",
          "frequency": 0.04129689186811447
        },
        {
          "action_code": "RAI",
          "frequency": 0
        }
      ]
    },
    {
      "name": "8d",
      "solutions": [
        {
          "action_code": "X",
          "frequency": 0.7440924048423767
        },
        {
          "action_code": "R1.8",
          "frequency": 0.08388570696115494
        },
        {
          "action_code": "R3.65",
          "frequency": 0.1307249814271927
        },
        {
          "action_code": "R7.15",
          "frequency": 0.04129689186811447
        },
        {
          "action_code": "RAI",
          "frequency": 0
        }
      ]
    },
    {
      "name": "8h",
      "solutions": [
        {
          "action_code": "X",
          "frequency": 0.8664681315422058
        },
        {
          "action_code": "R1.8",
          "frequency": 0.06766617298126221
        },
        {
          "action_code": "R3.65",
          "frequency": 0.0555228553712368
        },
        {
          "action_code": "R7.15",
          "frequency": 0.010342852212488651
        },
        {
          "action_code": "RAI",
          "frequency": 0
        }
      ]
    },
    {
      "name": "8s",
      "solutions": [
        {
          "action_code": "X",
          "frequency": 0.7440924048423767
        },
        {
          "action_code": "R1.8",
          "frequency": 0.08388570696115494
        },
        {
          "action_code": "R3.65",
          "frequency": 0.1307249814271927
        },
        {
          "action_code": "R7.15",
          "frequency": 0.04129689186811447
        },
        {
          "action_code": "RAI",
          "frequency": 0
        }
      ]
    },
    {
      "name": "9c",
      "solutions": [
        {
          "action_code": "X",
          "frequency": 0.7321481108665466
        },
        {
          "action_code": "R1.8",
          "frequency": 0.11189821362495422
        },
        {
          "action_code": "R3.65",
          "frequency": 0.11589311808347702
        },
        {
          "action_code": "R7.15",
          "frequency": 0.040060583502054214
        },
        {
          "action_code": "RAI",
          "frequency": 0
        }
      ]
    },
    {
      "name": "9d",
      "solutions": [
        {
          "action_code": "X",
          "frequency": 0.7321481108665466
        },
        {
          "action_code": "R1.8",
          "frequency": 0.11189821362495422
        },
        {
          "action_code": "R3.65",
          "frequency": 0.11589311808347702
        },
        {
          "action_code": "R7.15",
          "frequency": 0.040060583502054214
        },
        {
          "action_code": "RAI",
          "frequency": 0
        }
      ]
    },
    {
      "name": "9h",
      "solutions": [
        {
          "action_code": "X",
          "frequency": 0.8421251773834229
        },
        {
          "action_code": "R1.8",
          "frequency": 0.09381445497274399
        },
        {
          "action_code": "R3.65",
          "frequency": 0.06198487803339958
        },
        {
          "action_code": "R7.15",
          "frequency": 0.0020754924044013023
        },
        {
          "action_code": "RAI",
          "frequency": 0
        }
      ]
    },
    {
      "name": "9s",
      "solutions": [
        {
          "action_code": "X",
          "frequency": 0.7321481108665466
        },
        {
          "action_code": "R1.8",
          "frequency": 0.11189821362495422
        },
        {
          "action_code": "R3.65",
          "frequency": 0.11589311808347702
        },
        {
          "action_code": "R7.15",
          "frequency": 0.040060583502054214
        },
        {
          "action_code": "RAI",
          "frequency": 0
        }
      ]
    },
    {
      "name": "Tc",
      "solutions": [
        {
          "action_code": "X",
          "frequency": 0.8092067241668701
        },
        {
          "action_code": "R1.8",
          "frequency": 0.05733901634812355
        },
        {
          "action_code": "R3.65",
          "frequency": 0.09055225551128387
        },
        {
          "action_code": "R7.15",
          "frequency": 0.042902007699012756
        },
        {
          "action_code": "RAI",
          "frequency": 0
        }
      ]
    },
    {
      "name": "Td",
      "solutions": [
        {
          "action_code": "X",
          "frequency": 0.8092067241668701
        },
        {
          "action_code": "R1.8",
          "frequency": 0.05733901634812355
        },
        {
          "action_code": "R3.65",
          "frequency": 0.09055225551128387
        },
        {
          "action_code": "R7.15",
          "frequency": 0.042902007699012756
        },
        {
          "action_code": "RAI",
          "frequency": 0
        }
      ]
    },
    {
      "name": "Th",
      "solutions": [
        {
          "action_code": "X",
          "frequency": 0.8125666379928589
        },
        {
          "action_code": "R1.8",
          "frequency": 0.12523253262043
        },
        {
          "action_code": "R3.65",
          "frequency": 0.060086239129304886
        },
        {
          "action_code": "R7.15",
          "frequency": 0.002114600269123912
        },
        {
          "action_code": "RAI",
          "frequency": 0
        }
      ]
    },
    {
      "name": "Ts",
      "solutions": [
        {
          "action_code": "X",
          "frequency": 0.8092067241668701
        },
        {
          "action_code": "R1.8",
          "frequency": 0.05733901634812355
        },
        {
          "action_code": "R3.65",
          "frequency": 0.09055225551128387
        },
        {
          "action_code": "R7.15",
          "frequency": 0.042902007699012756
        },
        {
          "action_code": "RAI",
          "frequency": 0
        }
      ]
    },
    {
      "name": "Jc",
      "solutions": [
        {
          "action_code": "X",
          "frequency": 0.8583557605743408
        },
        {
          "action_code": "R1.8",
          "frequency": 0.06052165478467941
        },
        {
          "action_code": "R3.65",
          "frequency": 0.07809151709079742
        },
        {
          "action_code": "R7.15",
          "frequency": 0.0030310882721096277
        },
        {
          "action_code": "RAI",
          "frequency": 0
        }
      ]
    },
    {
      "name": "Jd",
      "solutions": [
        {
          "action_code": "X",
          "frequency": 0.8583557605743408
        },
        {
          "action_code": "R1.8",
          "frequency": 0.06052165478467941
        },
        {
          "action_code": "R3.65",
          "frequency": 0.07809151709079742
        },
        {
          "action_code": "R7.15",
          "frequency": 0.0030310882721096277
        },
        {
          "action_code": "RAI",
          "frequency": 0
        }
      ]
    },
    {
      "name": "Js",
      "solutions": [
        {
          "action_code": "X",
          "frequency": 0.8583557605743408
        },
        {
          "action_code": "R1.8",
          "frequency": 0.06052165478467941
        },
        {
          "action_code": "R3.65",
          "frequency": 0.07809151709079742
        },
        {
          "action_code": "R7.15",
          "frequency": 0.0030310882721096277
        },
        {
          "action_code": "RAI",
          "frequency": 0
        }
      ]
    },
    {
      "name": "Qc",
      "solutions": [
        {
          "action_code": "X",
          "frequency": 0.7243833541870117
        },
        {
          "action_code": "R1.8",
          "frequency": 0.13384684920310974
        },
        {
          "action_code": "R3.65",
          "frequency": 0.09810438752174377
        },
        {
          "action_code": "R7.15",
          "frequency": 0.04366542771458626
        },
        {
          "action_code": "RAI",
          "frequency": 0
        }
      ]
    },
    {
      "name": "Qd",
      "solutions": [
        {
          "action_code": "X",
          "frequency": 0.7243833541870117
        },
        {
          "action_code": "R1.8",
          "frequency": 0.13384684920310974
        },
        {
          "action_code": "R3.65",
          "frequency": 0.09810438752174377
        },
        {
          "action_code": "R7.15",
          "frequency": 0.04366542771458626
        },
        {
          "action_code": "RAI",
          "frequency": 0
        }
      ]
    },
    {
      "name": "Qh",
      "solutions": [
        {
          "action_code": "X",
          "frequency": 0.8516932129859924
        },
        {
          "action_code": "R1.8",
          "frequency": 0.08637040853500366
        },
        {
          "action_code": "R3.65",
          "frequency": 0.05819001421332359
        },
        {
          "action_code": "R7.15",
          "frequency": 0.0037463365588337183
        },
        {
          "action_code": "RAI",
          "frequency": 0
        }
      ]
    },
    {
      "name": "Qs",
      "solutions": [
        {
          "action_code": "X",
          "frequency": 0.7243833541870117
        },
        {
          "action_code": "R1.8",
          "frequency": 0.13384684920310974
        },
        {
          "action_code": "R3.65",
          "frequency": 0.09810438752174377
        },
        {
          "action_code": "R7.15",
          "frequency": 0.04366542771458626
        },
        {
          "action_code": "RAI",
          "frequency": 0
        }
      ]
    },
    {
      "name": "Kc",
      "solutions": [
        {
          "action_code": "X",
          "frequency": 0.8503894805908203
        },
        {
          "action_code": "R1.8",
          "frequency": 0.040075261145830154
        },
        {
          "action_code": "R3.65",
          "frequency": 0.10862977802753448
        },
        {
          "action_code": "R7.15",
          "frequency": 0.0009055082919076085
        },
        {
          "action_code": "RAI",
          "frequency": 0
        }
      ]
    },
    {
      "name": "Kd",
      "solutions": [
        {
          "action_code": "X",
          "frequency": 0.8503894805908203
        },
        {
          "action_code": "R1.8",
          "frequency": 0.040075261145830154
        },
        {
          "action_code": "R3.65",
          "frequency": 0.10862977802753448
        },
        {
          "action_code": "R7.15",
          "frequency": 0.0009055082919076085
        },
        {
          "action_code": "RAI",
          "frequency": 0
        }
      ]
    },
    {
      "name": "Ks",
      "solutions": [
        {
          "action_code": "X",
          "frequency": 0.8503894805908203
        },
        {
          "action_code": "R1.8",
          "frequency": 0.040075261145830154
        },
        {
          "action_code": "R3.65",
          "frequency": 0.10862977802753448
        },
        {
          "action_code": "R7.15",
          "frequency": 0.0009055082919076085
        },
        {
          "action_code": "RAI",
          "frequency": 0
        }
      ]
    },
    {
      "name": "Ac",
      "solutions": [
        {
          "action_code": "X",
          "frequency": 0.7275195121765137
        },
        {
          "action_code": "R1.8",
          "frequency": 0.10065539181232452
        },
        {
          "action_code": "R3.65",
          "frequency": 0.16612185537815094
        },
        {
          "action_code": "R7.15",
          "frequency": 0.0057032364420592785
        },
        {
          "action_code": "RAI",
          "frequency": 0
        }
      ]
    },
    {
      "name": "Ad",
      "solutions": [
        {
          "action_code": "X",
          "frequency": 0.7275195121765137
        },
        {
          "action_code": "R1.8",
          "frequency": 0.10065539181232452
        },
        {
          "action_code": "R3.65",
          "frequency": 0.16612185537815094
        },
        {
          "action_code": "R7.15",
          "frequency": 0.0057032364420592785
        },
        {
          "action_code": "RAI",
          "frequency": 0
        }
      ]
    },
    {
      "name": "Ah",
      "solutions": [
        {
          "action_code": "X",
          "frequency": 0.9005768299102783
        },
        {
          "action_code": "R1.8",
          "frequency": 0.08359585702419281
        },
        {
          "action_code": "R3.65",
          "frequency": 0.014776858501136303
        },
        {
          "action_code": "R7.15",
          "frequency": 0.0010504828533157706
        },
        {
          "action_code": "RAI",
          "frequency": 0
        }
      ]
    },
    {
      "name": "As",
      "solutions": [
        {
          "action_code": "X",
          "frequency": 0.7275195121765137
        },
        {
          "action_code": "R1.8",
          "frequency": 0.10065539181232452
        },
        {
          "action_code": "R3.65",
          "frequency": 0.16612185537815094
        },
        {
          "action_code": "R7.15",
          "frequency": 0.0057032364420592785
        },
        {
          "action_code": "RAI",
          "frequency": 0
        }
      ]
    }
  ],
  "player_solutions": [
    {
      "position": "BB",
      "is_hero": true,
      "relative_position": "OOP",
      "solutions": [
        {
          "name": "2c",
          "ev": 2.428425817633862,
          "eq": 0.483084398,
          "eqr": 0.9139851518088571
        },
        {
          "name": "2d",
          "ev": 2.4284258176338622,
          "eq": 0.483084398,
          "eqr": 0.9139851518088572
        },
        {
          "name": "2h",
          "ev": 2.221402209262573,
          "eq": 0.475055442,
          "eqr": 0.8501982612273985
        },
        {
          "name": "2s",
          "ev": 2.4284258176338627,
          "eq": 0.483084373,
          "eqr": 0.9139851991083149
        },
        {
          "name": "3c",
          "ev": 2.4304667214890037,
          "eq": 0.486218235,
          "eqr": 0.9088573987167057
        },
        {
          "name": "3d",
          "ev": 2.4304667214890037,
          "eq": 0.486218235,
          "eqr": 0.9088573987167057
        },
        {
          "name": "3h",
          "ev": 2.2218046878835964,
          "eq": 0.477297221,
          "eqr": 0.8463583505886544
        },
        {
          "name": "3s",
          "ev": 2.430466721489003,
          "eq": 0.4862182,
          "eqr": 0.9088574641400257
        },
        {
          "name": "4c",
          "ev": 2.408644279320122,
          "eq": 0.487232543,
          "eqr": 0.8988219892215809
        },
        {
          "name": "4d",
          "ev": 2.408644279320122,
          "eq": 0.487232543,
          "eqr": 0.8988219892215809
        },
        {
          "name": "4h",
          "ev": 2.2007941694785833,
          "eq": 0.476810117,
          "eqr": 0.8392112083700848
        },
        {
          "name": "4s",
          "ev": 2.4086442793201215,
          "eq": 0.487232504,
          "eqr": 0.8988220611668168
        },
        {
          "name": "5c",
          "ev": 2.2748756168727877,
          "eq": 0.473666946,
          "eqr": 0.8732164066232417
        },
        {
          "name": "5d",
          "ev": 2.274875616872787,
          "eq": 0.473666946,
          "eqr": 0.8732164066232414
        },
        {
          "name": "5s",
          "ev": 2.2748756168727864,
          "eq": 0.473666904,
          "eqr": 0.8732164840512582
        },
        {
          "name": "6c",
          "ev": 2.380192282920781,
          "eq": 0.481869756,
          "eqr": 0.8980896349475892
        },
        {
          "name": "6d",
          "ev": 2.3801922829207816,
          "eq": 0.481869756,
          "eqr": 0.8980896349475893
        },
        {
          "name": "6h",
          "ev": 2.176981057699933,
          "eq": 0.47424995,
          "eqr": 0.8346120811686415
        },
        {
          "name": "6s",
          "ev": 2.380192282920781,
          "eq": 0.481869717,
          "eqr": 0.8980897076342398
        },
        {
          "name": "7c",
          "ev": 2.371749804504839,
          "eq": 0.482250064,
          "eqr": 0.8941984032223955
        },
        {
          "name": "7d",
          "ev": 2.3717498045048386,
          "eq": 0.482250064,
          "eqr": 0.8941984032223953
        },
        {
          "name": "7h",
          "ev": 2.1715363959065894,
          "eq": 0.473691002,
          "eqr": 0.8335070701970891
        },
        {
          "name": "7s",
          "ev": 2.371749804504838,
          "eq": 0.482250021,
          "eqr": 0.8941984829539237
        },
        {
          "name": "8c",
          "ev": 2.3484933438481805,
          "eq": 0.477110273,
          "eqr": 0.8949687607975237
        },
        {
          "name": "8d",
          "ev": 2.34849334384818,
          "eq": 0.477110273,
          "eqr": 0.8949687607975236
        },
        {
          "name": "8h",
          "ev": 2.1804631306134605,
          "eq": 0.472957354,
          "eqr": 0.8382316895525429
        },
        {
          "name": "8s",
          "ev": 2.348493343848181,
          "eq": 0.477110234,
          "eqr": 0.894968833954164
        },
        {
          "name": "9c",
          "ev": 2.3361427080326305,
          "eq": 0.472504051,
          "eqr": 0.898940905889284
        },
        {
          "name": "9d",
          "ev": 2.3361427080326305,
          "eq": 0.472504051,
          "eqr": 0.898940905889284
        },
        {
          "name": "9h",
          "ev": 2.158543679623629,
          "eq": 0.468752234,
          "eqr": 0.8372493158172258
        },
        {
          "name": "9s",
          "ev": 2.33614270803263,
          "eq": 0.472504012,
          "eqr": 0.8989409800869508
        },
        {
          "name": "Tc",
          "ev": 2.1833990893614224,
          "eq": 0.453925578,
          "eqr": 0.8745522875363673
        },
        {
          "name": "Td",
          "ev": 2.1833990893614224,
          "eq": 0.453925578,
          "eqr": 0.8745522875363673
        },
        {
          "name": "Th",
          "ev": 2.1319677756406317,
          "eq": 0.462159849,
          "eqr": 0.838736868857539
        },
        {
          "name": "Ts",
          "ev": 2.183399089361422,
          "eq": 0.45392555,
          "eqr": 0.8745523414823589
        },
        {
          "name": "Jc",
          "ev": 2.174539488021251,
          "eq": 0.464041125,
          "eqr": 0.8520167603762788
        },
        {
          "name": "Jd",
          "ev": 2.1745394880212516,
          "eq": 0.464041125,
          "eqr": 0.8520167603762789
        },
        {
          "name": "Js",
          "ev": 2.174539488021251,
          "eq": 0.464041089,
          "eqr": 0.8520168264751741
        },
        {
          "name": "Qc",
          "ev": 2.318254869826615,
          "eq": 0.468920429,
          "eqr": 0.8988750742250579
        },
        {
          "name": "Qd",
          "ev": 2.3182548698266148,
          "eq": 0.468920429,
          "eqr": 0.8988750742250576
        },
        {
          "name": "Qh",
          "ev": 2.1457273819534035,
          "eq": 0.466553692,
          "eqr": 0.8362001157720025
        },
        {
          "name": "Qs",
          "ev": 2.3182548698266148,
          "eq": 0.468920401,
          "eqr": 0.8988751278983506
        },
        {
          "name": "Kc",
          "ev": 2.181678326104965,
          "eq": 0.463543229,
          "eqr": 0.8557320261591808
        },
        {
          "name": "Kd",
          "ev": 2.1816783261049655,
          "eq": 0.463543229,
          "eqr": 0.855732026159181
        },
        {
          "name": "Ks",
          "ev": 2.181678326104966,
          "eq": 0.463542305,
          "eqr": 0.8557337319288242
        },
        {
          "name": "Ac",
          "ev": 2.258442033558716,
          "eq": 0.461931572,
          "eqr": 0.8889321474727059
        },
        {
          "name": "Ad",
          "ev": 2.2584420335587154,
          "eq": 0.461931572,
          "eqr": 0.8889321474727057
        },
        {
          "name": "Ah",
          "ev": 2.028561599331873,
          "eq": 0.454785117,
          "eqr": 0.8109970355443802
        },
        {
          "name": "As",
          "ev": 2.2584420335587154,
          "eq": 0.461930801,
          "eqr": 0.888933631172611
        }
      ],
      "total_ev": 2.284157045548567,
      "total_eq": 0.4728817242244899,
      "total_eqr": 0.8779360563906555
    },
    {
      "position": "BTN",
      "is_hero": false,
      "relative_position": "IP",
      "solutions": [
        {
          "name": "2c",
          "ev": 2.536355377796362,
          "eq": 0.516915484,
          "eqr": 0.892129443806141
        },
        {
          "name": "2d",
          "ev": 2.536355377796362,
          "eq": 0.516915484,
          "eqr": 0.892129443806141
        },
        {
          "name": "2h",
          "ev": 2.770381313525166,
          "eq": 0.524944428,
          "eqr": 0.9595409847234572
        },
        {
          "name": "2s",
          "ev": 2.536355377796361,
          "eq": 0.516915482,
          "eqr": 0.8921294472578828
        },
        {
          "name": "3c",
          "ev": 2.5315997751389356,
          "eq": 0.513781635,
          "eqr": 0.8958881299972492
        },
        {
          "name": "3d",
          "ev": 2.5315997751389356,
          "eq": 0.513781635,
          "eqr": 0.8958881299972492
        },
        {
          "name": "3h",
          "ev": 2.7678870991936195,
          "eq": 0.522702683,
          "eqr": 0.9627886295991814
        },
        {
          "name": "3s",
          "ev": 2.5315997751389356,
          "eq": 0.513781633,
          "eqr": 0.8958881334846767
        },
        {
          "name": "4c",
          "ev": 2.5532068973413566,
          "eq": 0.51276728,
          "eqr": 0.9053218759984971
        },
        {
          "name": "4d",
          "ev": 2.5532068973413566,
          "eq": 0.51276728,
          "eqr": 0.9053218759984971
        },
        {
          "name": "4h",
          "ev": 2.787652804394055,
          "eq": 0.523189737,
          "eqr": 0.9687612898172784
        },
        {
          "name": "4s",
          "ev": 2.553206897341357,
          "eq": 0.512767281,
          "eqr": 0.9053218742329363
        },
        {
          "name": "5c",
          "ev": 2.709859410261296,
          "eq": 0.526333046,
          "eqr": 0.9361025584485136
        },
        {
          "name": "5d",
          "ev": 2.7098594102612945,
          "eq": 0.526333046,
          "eqr": 0.9361025584485132
        },
        {
          "name": "5s",
          "ev": 2.709859410261292,
          "eq": 0.526333048,
          "eqr": 0.9361025548914392
        },
        {
          "name": "6c",
          "ev": 2.5800542444020955,
          "eq": 0.518130172,
          "eqr": 0.9053724277409422
        },
        {
          "name": "6d",
          "ev": 2.5800542444020946,
          "eq": 0.518130172,
          "eqr": 0.9053724277409418
        },
        {
          "name": "6h",
          "ev": 2.809991275206493,
          "eq": 0.52575005,
          "eqr": 0.9717688178688688
        },
        {
          "name": "6s",
          "ev": 2.580054244402094,
          "eq": 0.51813017,
          "eqr": 0.9053724312357099
        },
        {
          "name": "7c",
          "ev": 2.581467354309431,
          "eq": 0.517749777,
          "eqr": 0.906533854061965
        },
        {
          "name": "7d",
          "ev": 2.5814673543094293,
          "eq": 0.517749777,
          "eqr": 0.9065338540619644
        },
        {
          "name": "7h",
          "ev": 2.814629540783447,
          "eq": 0.526308875,
          "eqr": 0.9723393427423969
        },
        {
          "name": "7s",
          "ev": 2.581467354309431,
          "eq": 0.517749776,
          "eqr": 0.9065338558128762
        },
        {
          "name": "8c",
          "ev": 2.613116657251939,
          "eq": 0.522889621,
          "eqr": 0.9086279406191398
        },
        {
          "name": "8d",
          "ev": 2.613116657251938,
          "eq": 0.522889621,
          "eqr": 0.9086279406191394
        },
        {
          "name": "8h",
          "ev": 2.8067268997781856,
          "eq": 0.527042595,
          "eqr": 0.9682594663489238
        },
        {
          "name": "8s",
          "ev": 2.6131166572519398,
          "eq": 0.522889623,
          "eqr": 0.9086279371437301
        },
        {
          "name": "9c",
          "ev": 2.634729868903832,
          "eq": 0.527495892,
          "eqr": 0.9081431753522571
        },
        {
          "name": "9d",
          "ev": 2.6347298689038308,
          "eq": 0.527495892,
          "eqr": 0.9081431753522566
        },
        {
          "name": "9h",
          "ev": 2.8282094963915583,
          "eq": 0.531247774,
          "eqr": 0.9679474128673314
        },
        {
          "name": "9s",
          "ev": 2.6347298689038303,
          "eq": 0.527495893,
          "eqr": 0.9081431736306447
        },
        {
          "name": "Tc",
          "ev": 2.8027339541235747,
          "eq": 0.546074338,
          "eqr": 0.9331842868229265
        },
        {
          "name": "Td",
          "ev": 2.802733954123575,
          "eq": 0.546074338,
          "eqr": 0.9331842868229266
        },
        {
          "name": "Th",
          "ev": 2.851336935301512,
          "eq": 0.537840111,
          "eqr": 0.9639015140831466
        },
        {
          "name": "Ts",
          "ev": 2.802733954123576,
          "eq": 0.546074338,
          "eqr": 0.933184286822927
        },
        {
          "name": "Jc",
          "ev": 2.833318662971418,
          "eq": 0.535958858,
          "eqr": 0.9611723738186357
        },
        {
          "name": "Jd",
          "ev": 2.8333186629714198,
          "eq": 0.535958858,
          "eqr": 0.9611723738186364
        },
        {
          "name": "Js",
          "ev": 2.8333186629714175,
          "eq": 0.535958855,
          "eqr": 0.9611723791987448
        },
        {
          "name": "Qc",
          "ev": 2.6633300786632,
          "eq": 0.531079548,
          "eqr": 0.9118065915131384
        },
        {
          "name": "Qd",
          "ev": 2.6633300786631997,
          "eq": 0.531079548,
          "eqr": 0.9118065915131383
        },
        {
          "name": "Qh",
          "ev": 2.843296549661986,
          "eq": 0.533446197,
          "eqr": 0.9691005614750912
        },
        {
          "name": "Qs",
          "ev": 2.6633300786631993,
          "eq": 0.531079547,
          "eqr": 0.9118065932300308
        },
        {
          "name": "Kc",
          "ev": 2.819323976326594,
          "eq": 0.536456801,
          "eqr": 0.9555370691108229
        },
        {
          "name": "Kd",
          "ev": 2.8193239763265954,
          "eq": 0.536456801,
          "eqr": 0.9555370691108234
        },
        {
          "name": "Ks",
          "ev": 2.8193239763265954,
          "eq": 0.53645766,
          "eqr": 0.955535539062129
        },
        {
          "name": "Ac",
          "ev": 2.721109106933986,
          "eq": 0.538068384,
          "eqr": 0.9194874203046165
        },
        {
          "name": "Ad",
          "ev": 2.721109106933986,
          "eq": 0.538068384,
          "eqr": 0.9194874203046165
        },
        {
          "name": "Ah",
          "ev": 2.972283799486101,
          "eq": 0.545214996,
          "eqr": 0.9911965742596709
        },
        {
          "name": "As",
          "ev": 2.721109106933986,
          "eq": 0.53806909,
          "eqr": 0.9194862138459464
        }
      ],
      "total_ev": 2.6937349348366166,
      "total_eq": 0.5271181941632653,
      "total_eqr": 0.9288474144658109
    }
  ],
  "totals": [
    {
      "action_code": "X",
      "frequency": 0.7809077841894967
    },
    {
      "action_code": "R1.8",
      "frequency": 0.07835145446718955
    },
    {
      "action_code": "R3.65",
      "frequency": 0.11042268275834467
    },
    {
      "action_code": "R7.15",
      "frequency": 0.030267013056317762
    },
    {
      "action_code": "RAI",
      "frequency": 0.000051069980943385435
    }
  ],
  "game_point": {
    "game": {
      "players": [
        {
          "position": "UTG",
          "relative_postflop_position": null,
          "hand": null,
          "is_dealer": false,
          "is_folded": true,
          "is_hero": false,
          "is_active": false,
          "stack": "100.000",
          "current_stack": "100.000",
          "chips_on_table": "0.00",
          "bounty": null,
          "chips_by_denomination": []
        },
        {
          "position": "HJ",
          "relative_postflop_position": null,
          "hand": null,
          "is_dealer": false,
          "is_folded": true,
          "is_hero": false,
          "is_active": false,
          "stack": "100.000",
          "current_stack": "100.000",
          "chips_on_table": "0.00",
          "bounty": null,
          "chips_by_denomination": []
        },
        {
          "position": "CO",
          "relative_postflop_position": null,
          "hand": null,
          "is_dealer": false,
          "is_folded": true,
          "is_hero": false,
          "is_active": false,
          "stack": "100.000",
          "current_stack": "100.000",
          "chips_on_table": "0.00",
          "bounty": null,
          "chips_by_denomination": []
        },
        {
          "position": "BTN",
          "relative_postflop_position": "IP",
          "hand": null,
          "is_dealer": true,
          "is_folded": false,
          "is_hero": false,
          "is_active": false,
          "stack": "100.000",
          "current_stack": "97.500",
          "chips_on_table": "0.00",
          "bounty": null,
          "chips_by_denomination": []
        },
        {
          "position": "SB",
          "relative_postflop_position": null,
          "hand": null,
          "is_dealer": false,
          "is_folded": true,
          "is_hero": false,
          "is_active": false,
          "stack": "100.000",
          "current_stack": "99.500",
          "chips_on_table": "0.00",
          "bounty": null,
          "chips_by_denomination": []
        },
        {
          "position": "BB",
          "relative_postflop_position": "OOP",
          "hand": null,
          "is_dealer": false,
          "is_folded": false,
          "is_hero": false,
          "is_active": true,
          "stack": "100.000",
          "current_stack": "97.500",
          "chips_on_table": "0.00",
          "bounty": null,
          "chips_by_denomination": []
        }
      ],
      "current_street": {
        "type": "TURN",
        "start_pot": "5.500",
        "start_pot_by_denomination": [
          {
            "denomination": "5.0",
            "amount": 1
          },
          {
            "denomination": "0.5",
            "amount": 1
          }
        ],
        "end_pot": "5.500",
        "end_pot_by_denomination": [
          {
            "denomination": "5.0",
            "amount": 1
          },
          {
            "denomination": "0.5",
            "amount": 1
          }
        ]
      },
      "pot": "5.500",
      "pot_by_denomination": [
        {
          "denomination": "5.0",
          "amount": 1
        },
        {
          "denomination": "0.5",
          "amount": 1
        }
      ],
      "pot_odds": null,
      "active_position": "BB",
      "board": "KhJh5h",
      "bet_display_name": "BET"
    },
    "available_actions": [
      {
        "action": {
          "code": "X",
          "position": "BB",
          "type": "CHECK",
          "betsize": "0.000",
          "allin": false,
          "is_hand_end": false,
          "is_showdown": false,
          "next_street": false,
          "display_name": "CHECK",
          "simple_group": "CHECK",
          "advanced_group": "CHECK",
          "betsize_by_pot": null,
          "next_position": "BTN"
        },
        "frequency": 0,
        "is_solution_end": false,
        "can_be_solved_by_ai": false,
        "next_position": "BTN",
        "selected": false
      },
      {
        "action": {
          "code": "R1.8",
          "position": "BB",
          "type": "RAISE",
          "betsize": "1.800",
          "allin": false,
          "is_hand_end": false,
          "is_showdown": false,
          "next_street": false,
          "display_name": "BET",
          "simple_group": "RAISE",
          "advanced_group": "BET_SMALL",
          "betsize_by_pot": "0.32727273",
          "next_position": "BTN"
        },
        "frequency": 0,
        "is_solution_end": false,
        "can_be_solved_by_ai": false,
        "next_position": "BTN",
        "selected": false
      },
      {
        "action": {
          "code": "R3.65",
          "position": "BB",
          "type": "RAISE",
          "betsize": "3.650",
          "allin": false,
          "is_hand_end": false,
          "is_showdown": false,
          "next_street": false,
          "display_name": "BET",
          "simple_group": "RAISE",
          "advanced_group": "BET_MEDIUM",
          "betsize_by_pot": "0.66363636",
          "next_position": "BTN"
        },
        "frequency": 0,
        "is_solution_end": false,
        "can_be_solved_by_ai": false,
        "next_position": "BTN",
        "selected": false
      },
      {
        "action": {
          "code": "R7.15",
          "position": "BB",
          "type": "RAISE",
          "betsize": "7.150",
          "allin": false,
          "is_hand_end": false,
          "is_showdown": false,
          "next_street": false,
          "display_name": "BET",
          "simple_group": "RAISE",
          "advanced_group": "BET_OVERBET",
          "betsize_by_pot": "1.30000000",
          "next_position": "BTN"
        },
        "frequency": 0,
        "is_solution_end": false,
        "can_be_solved_by_ai": false,
        "next_position": "BTN",
        "selected": false
      },
      {
        "action": {
          "code": "RAI",
          "position": "BB",
          "type": "RAISE",
          "betsize": "97.500",
          "allin": true,
          "is_hand_end": false,
          "is_showdown": false,
          "next_street": false,
          "display_name": "ALLIN",
          "simple_group": "RAISE",
          "advanced_group": "BET_OVERBET",
          "betsize_by_pot": "17.72727273",
          "next_position": "BTN"
        },
        "frequency": 0,
        "is_solution_end": false,
        "can_be_solved_by_ai": false,
        "next_position": "BTN",
        "selected": false
      }
    ],
    "custom_solution_id": null,
    "is_node_locked": false,
    "is_edited": false,
    "available_node_edits": null
  }
}