{
  "solutions": [
    {
      "name": "2c",
      "solutions": [
        {
          "action_code": "X",
          "frequency": 0.5119407773017883
        },
        {
          "action_code": "R11.5",
          "frequency": 0.41046079993247986
        },
        {
          "action_code": "R23.05",
          "frequency": 0.07759842276573181
        },
        {
          "action_code": "R45.35",
          "frequency": 0
        },
        {
          "action_code": "RAI",
          "frequency": 0
        }
      ]
    },
    {
      "name": "2d",
      "solutions": [
        {
          "action_code": "X",
          "frequency": 0.5119407773017883
        },
        {
          "action_code": "R11.5",
          "frequency": 0.41046079993247986
        },
        {
          "action_code": "R23.05",
          "frequency": 0.07759842276573181
        },
        {
          "action_code": "R45.35",
          "frequency": 0
        },
        {
          "action_code": "RAI",
          "frequency": 0
        }
      ]
    },
    {
      "name": "2h",
      "solutions": [
        {
          "action_code": "X",
          "frequency": 0.7285309433937073
        },
        {
          "action_code": "R11.5",
          "frequency": 0.07406735420227051
        },
        {
          "action_code": "R23.05",
          "frequency": 0.1974017322063446
        },
        {
          "action_code": "R45.35",
          "frequency": 0
        },
        {
          "action_code": "RAI",
          "frequency": 0
        }
      ]
    },
    {
      "name": "2s",
      "solutions": [
        {
          "action_code": "X",
          "frequency": 0.5119407773017883
        },
        {
          "action_code": "R11.5",
          "frequency": 0.41046079993247986
        },
        {
          "action_code": "R23.05",
          "frequency": 0.07759842276573181
        },
        {
          "action_code": "R45.35",
          "frequency": 0
        },
        {
          "action_code": "RAI",
          "frequency": 0
        }
      ]
    },
    {
      "name": "3c",
      "solutions": [
        {
          "action_code": "X",
          "frequency": 0.5035870671272278
        },
        {
          "action_code": "R11.5",
          "frequency": 0.4151848256587982
        },
        {
          "action_code": "R23.05",
          "frequency": 0.0812281146645546
        },
        {
          "action_code": "R45.35",
          "frequency": 0
        },
        {
          "action_code": "RAI",
          "frequency": 0
        }
      ]
    },
    {
      "name": "3d",
      "solutions": [
        {
          "action_code": "X",
          "frequency": 0.5035870671272278
        },
        {
          "action_code": "R11.5",
          "frequency": 0.4151848256587982
        },
        {
          "action_code": "R23.05",
          "frequency": 0.0812281146645546
        },
        {
          "action_code": "R45.35",
          "frequency": 0
        },
        {
          "action_code": "RAI",
          "frequency": 0
        }
      ]
    },
    {
      "name": "3h",
      "solutions": [
        {
          "action_code": "X",
          "frequency": 0.7136539816856384
        },
        {
          "action_code": "R11.5",
          "frequency": 0.08806838095188141
        },
        {
          "action_code": "R23.05",
          "frequency": 0.19827762246131897
        },
        {
          "action_code": "R45.35",
          "frequency": 0
        },
        {
          "action_code": "RAI",
          "frequency": 0
        }
      ]
    },
    {
      "name": "3s",
      "solutions": [
        {
          "action_code": "X",
          "frequency": 0.5035870671272278
        },
        {
          "action_code": "R11.5",
          "frequency": 0.4151848256587982
        },
        {
          "action_code": "R23.05",
          "frequency": 0.0812281146645546
        },
        {
          "action_code": "R45.35",
          "frequency": 0
        },
        {
          "action_code": "RAI",
          "frequency": 0
        }
      ]
    },
    {
      "name": "4c",
      "solutions": [
        {
          "action_code": "X",
          "frequency": 0.5098690390586853
        },
        {
          "action_code": "R11.5",
          "frequency": 0.42264804244041443
        },
        {
          "action_code": "R23.05",
          "frequency": 0.06748289614915848
        },
        {
          "action_code": "R45.35",
          "frequency": 0
        },
        {
          "action_code": "RAI",
          "frequency": 0
        }
      ]
    },
    {
      "name": "4d",
      "solutions": [
        {
          "action_code": "X",
          "frequency": 0.5098690390586853
        },
        {
          "action_code": "R11.5",
          "frequency": 0.42264804244041443
        },
        {
          "action_code": "R23.05",
          "frequency": 0.06748289614915848
        },
        {
          "action_code": "R45.35",
          "frequency": 0
        },
        {
          "action_code": "RAI",
          "frequency": 0
        }
      ]
    },
    {
      "name": "4h",
      "solutions": [
        {
          "action_code": "X",
          "frequency": 0.7056237459182739
        },
        {
          "action_code": "R11.5",
          "frequency": 0.11353619396686554
        },
        {
          "action_code": "R23.05",
          "frequency": 0.18084008991718292
        },
        {
          "action_code": "R45.35",
          "frequency": 0
        },
        {
          "action_code": "RAI",
          "frequency": 0
        }
      ]
    },
    {
      "name": "4s",
      "solutions": [
        {
          "action_code": "X",
          "frequency": 0.5098690390586853
        },
        {
          "action_code": "R11.5",
          "frequency": 0.42264804244041443
        },
        {
          "action_code": "R23.05",
          "frequency": 0.06748289614915848
        },
        {
          "action_code": "R45.35",
          "frequency": 0
        },
        {
          "action_code": "RAI",
          "frequency": 0
        }
      ]
    },
    {
      "name": "5c",
      "solutions": [
        {
          "action_code": "X",
          "frequency": 0.49073976278305054
        },
        {
          "action_code": "R11.5",
          "frequency": 0.45725950598716736
        },
        {
          "action_code": "R23.05",
          "frequency": 0.0520007461309433
        },
        {
          "action_code": "R45.35",
          "frequency": 0
        },
        {
          "action_code": "RAI",
          "frequency": 0
        }
      ]
    },
    {
      "name": "5d",
      "solutions": [
        {
          "action_code": "X",
          "frequency": 0.49073976278305054
        },
        {
          "action_code": "R11.5",
          "frequency": 0.45725950598716736
        },
        {
          "action_code": "R23.05",
          "frequency": 0.0520007461309433
        },
        {
          "action_code": "R45.35",
          "frequency": 0
        },
        {
          "action_code": "RAI",
          "frequency": 0
        }
      ]
    },
    {
      "name": "5h",
      "solutions": [
        {
          "action_code": "X",
          "frequency": 0.6874291300773621
        },
        {
          "action_code": "R11.5",
          "frequency": 0.13218513131141663
        },
        {
          "action_code": "R23.05",
          "frequency": 0.1803857386112213
        },
        {
          "action_code": "R45.35",
          "frequency": 0
        },
        {
          "action_code": "RAI",
          "frequency": 0
        }
      ]
    },
    {
      "name": "5s",
      "solutions": [
        {
          "action_code": "X",
          "frequency": 0.49073976278305054
        },
        {
          "action_code": "R11.5",
          "frequency": 0.45725950598716736
        },
        {
          "action_code": "R23.05",
          "frequency": 0.0520007461309433
        },
        {
          "action_code": "R45.35",
          "frequency": 0
        },
        {
          "action_code": "RAI",
          "frequency": 0
        }
      ]
    },
    {
      "name": "6c",
      "solutions": [
        {
          "action_code": "X",
          "frequency": 0.5200236439704895
        },
        {
          "action_code": "R11.5",
          "frequency": 0.4402969479560852
        },
        {
          "action_code": "R23.05",
          "frequency": 0.039679404348134995
        },
        {
          "action_code": "R45.35",
          "frequency": 0
        },
        {
          "action_code": "RAI",
          "frequency": 0
        }
      ]
    },
    {
      "name": "6d",
      "solutions": [
        {
          "action_code": "X",
          "frequency": 0.5200236439704895
        },
        {
          "action_code": "R11.5",
          "frequency": 0.4402969479560852
        },
        {
          "action_code": "R23.05",
          "frequency": 0.039679404348134995
        },
        {
          "action_code": "R45.35",
          "frequency": 0
        },
        {
          "action_code": "RAI",
          "frequency": 0
        }
      ]
    },
    {
      "name": "6h",
      "solutions": [
        {
          "action_code": "X",
          "frequency": 0.661605179309845
        },
        {
          "action_code": "R11.5",
          "frequency": 0.12280353903770447
        },
        {
          "action_code": "R23.05",
          "frequency": 0.21559129655361176
        },
        {
          "action_code": "R45.35",
          "frequency": 0
        },
        {
          "action_code": "RAI",
          "frequency": 0
        }
      ]
    },
    {
      "name": "6s",
      "solutions": [
        {
          "action_code": "X",
          "frequency": 0.5200236439704895
        },
        {
          "action_code": "R11.5",
          "frequency": 0.4402969479560852
        },
        {
          "action_code": "R23.05",
          "frequency": 0.039679404348134995
        },
        {
          "action_code": "R45.35",
          "frequency": 0
        },
        {
          "action_code": "RAI",
          "frequency": 0
        }
      ]
    },
    {
      "name": "7c",
      "solutions": [
        {
          "action_code": "X",
          "frequency": 0.5288417935371399
        },
        {
          "action_code": "R11.5",
          "frequency": 0.47030216455459595
        },
        {
          "action_code": "R23.05",
          "frequency": 0.0008560240385122597
        },
        {
          "action_code": "R45.35",
          "frequency": 0
        },
        {
          "action_code": "RAI",
          "frequency": 0
        }
      ]
    },
    {
      "name": "7d",
      "solutions": [
        {
          "action_code": "X",
          "frequency": 0.5288417935371399
        },
        {
          "action_code": "R11.5",
          "frequency": 0.47030216455459595
        },
        {
          "action_code": "R23.05",
          "frequency": 0.0008560240385122597
        },
        {
          "action_code": "R45.35",
          "frequency": 0
        },
        {
          "action_code": "RAI",
          "frequency": 0
        }
      ]
    },
    {
      "name": "7h",
      "solutions": [
        {
          "action_code": "X",
          "frequency": 0.6850633025169373
        },
        {
          "action_code": "R11.5",
          "frequency": 0.14096805453300476
        },
        {
          "action_code": "R23.05",
          "frequency": 0.17396865785121918
        },
        {
          "action_code": "R45.35",
          "frequency": 0
        },
        {
          "action_code": "RAI",
          "frequency": 0
        }
      ]
    },
    {
      "name": "7s",
      "solutions": [
        {
          "action_code": "X",
          "frequency": 0.5288417935371399
        },
        {
          "action_code": "R11.5",
          "frequency": 0.47030216455459595
        },
        {
          "action_code": "R23.05",
          "frequency": 0.0008560240385122597
        },
        {
          "action_code": "R45.35",
          "frequency": 0
        },
        {
          "action_code": "RAI",
          "frequency": 0
        }
      ]
    },
    {
      "name": "8c",
      "solutions": [
        {
          "action_code": "X",
          "frequency": 0.5752350091934204
        },
        {
          "action_code": "R11.5",
          "frequency": 0.3863268494606018
        },
        {
          "action_code": "R23.05",
          "frequency": 0.03843815252184868
        },
        {
          "action_code": "R45.35",
          "frequency": 0
        },
        {
          "action_code": "RAI",
          "frequency": 0
        }
      ]
    },
    {
      "name": "8d",
      "solutions": [
        {
          "action_code": "X",
          "frequency": 0.5752350091934204
        },
        {
          "action_code": "R11.5",
          "frequency": 0.3863268494606018
        },
        {
          "action_code": "R23.05",
          "frequency": 0.03843815252184868
        },
        {
          "action_code": "R45.35",
          "frequency": 0
        },
        {
          "action_code": "RAI",
          "frequency": 0
        }
      ]
    },
    {
      "name": "8s",
      "solutions": [
        {
          "action_code": "X",
          "frequency": 0.5752350091934204
        },
        {
          "action_code": "R11.5",
          "frequency": 0.3863268494606018
        },
        {
          "action_code": "R23.05",
          "frequency": 0.03843815252184868
        },
        {
          "action_code": "R45.35",
          "frequency": 0
        },
        {
          "action_code": "RAI",
          "frequency": 0
        }
      ]
    },
    {
      "name": "9c",
      "solutions": [
        {
          "action_code": "X",
          "frequency": 0.6670402884483337
        },
        {
          "action_code": "R11.5",
          "frequency": 0.33295971155166626
        },
        {
          "action_code": "R23.05",
          "frequency": 0
        },
        {
          "action_code": "R45.35",
          "frequency": 0
        },
        {
          "action_code": "RAI",
          "frequency": 0
        }
      ]
    },
    {
      "name": "9d",
      "solutions": [
        {
          "action_code": "X",
          "frequency": 0.6670402884483337
        },
        {
          "action_code": "R11.5",
          "frequency": 0.33295971155166626
        },
        {
          "action_code": "R23.05",
          "frequency": 0
        },
        {
          "action_code": "R45.35",
          "frequency": 0
        },
        {
          "action_code": "RAI",
          "frequency": 0
        }
      ]
    },
    {
      "name": "9h",
      "solutions": [
        {
          "action_code": "X",
          "frequency": 0.6950709223747253
        },
        {
          "action_code": "R11.5",
          "frequency": 0.1103869155049324
        },
        {
          "action_code": "R23.05",
          "frequency": 0.19454213976860046
        },
        {
          "action_code": "R45.35",
          "frequency": 0
        },
        {
          "action_code": "RAI",
          "frequency": 0
        }
      ]
    },
    {
      "name": "9s",
      "solutions": [
        {
          "action_code": "X",
          "frequency": 0.6670402884483337
        },
        {
          "action_code": "R11.5",
          "frequency": 0.33295971155166626
        },
        {
          "action_code": "R23.05",
          "frequency": 0
        },
        {
          "action_code": "R45.35",
          "frequency": 0
        },
        {
          "action_code": "RAI",
          "frequency": 0
        }
      ]
    },
    {
      "name": "Tc",
      "solutions": [
        {
          "action_code": "X",
          "frequency": 0.375575989484787
        },
        {
          "action_code": "R11.5",
          "frequency": 0.6224008202552795
        },
        {
          "action_code": "R23.05",
          "frequency": 0.002023170003667474
        },
        {
          "action_code": "R45.35",
          "frequency": 0
        },
        {
          "action_code": "RAI",
          "frequency": 0
        }
      ]
    },
    {
      "name": "Td",
      "solutions": [
        {
          "action_code": "X",
          "frequency": 0.375575989484787
        },
        {
          "action_code": "R11.5",
          "frequency": 0.6224008202552795
        },
        {
          "action_code": "R23.05",
          "frequency": 0.002023170003667474
        },
        {
          "action_code": "R45.35",
          "frequency": 0
        },
        {
          "action_code": "RAI",
          "frequency": 0
        }
      ]
    },
    {
      "name": "Th",
      "solutions": [
        {
          "action_code": "X",
          "frequency": 0.7460137605667114
        },
        {
          "action_code": "R11.5",
          "frequency": 0.11011952906847
        },
        {
          "action_code": "R23.05",
          "frequency": 0.14386670291423798
        },
        {
          "action_code": "R45.35",
          "frequency": 0
        },
        {
          "action_code": "RAI",
          "frequency": 0
        }
      ]
    },
    {
      "name": "Ts",
      "solutions": [
        {
          "action_code": "X",
          "frequency": 0.375575989484787
        },
        {
          "action_code": "R11.5",
          "frequency": 0.6224008202552795
        },
        {
          "action_code": "R23.05",
          "frequency": 0.002023170003667474
        },
        {
          "action_code": "R45.35",
          "frequency": 0
        },
        {
          "action_code": "RAI",
          "frequency": 0
        }
      ]
    },
    {
      "name": "Jc",
      "solutions": [
        {
          "action_code": "X",
          "frequency": 0.7198663353919983
        },
        {
          "action_code": "R11.5",
          "frequency": 0.258605033159256
        },
        {
          "action_code": "R23.05",
          "frequency": 0.021528631448745728
        },
        {
          "action_code": "R45.35",
          "frequency": 0
        },
        {
          "action_code": "RAI",
          "frequency": 0
        }
      ]
    },
    {
      "name": "Jd",
      "solutions": [
        {
          "action_code": "X",
          "frequency": 0.7198663353919983
        },
        {
          "action_code": "R11.5",
          "frequency": 0.258605033159256
        },
        {
          "action_code": "R23.05",
          "frequency": 0.021528631448745728
        },
        {
          "action_code": "R45.35",
          "frequency": 0
        },
        {
          "action_code": "RAI",
          "frequency": 0
        }
      ]
    },
    {
      "name": "Js",
      "solutions": [
        {
          "action_code": "X",
          "frequency": 0.7198663353919983
        },
        {
          "action_code": "R11.5",
          "frequency": 0.258605033159256
        },
        {
          "action_code": "R23.05",
          "frequency": 0.021528631448745728
        },
        {
          "action_code": "R45.35",
          "frequency": 0
        },
        {
          "action_code": "RAI",
          "frequency": 0
        }
      ]
    },
    {
      "name": "Qc",
      "solutions": [
        {
          "action_code": "X",
          "frequency": 0.45037153363227844
        },
        {
          "action_code": "R11.5",
          "frequency": 0.5490552186965942
        },
        {
          "action_code": "R23.05",
          "frequency": 0.0005732597201131284
        },
        {
          "action_code": "R45.35",
          "frequency": 0
        },
        {
          "action_code": "RAI",
          "frequency": 0
        }
      ]
    },
    {
      "name": "Qd",
      "solutions": [
        {
          "action_code": "X",
          "frequency": 0.45037153363227844
        },
        {
          "action_code": "R11.5",
          "frequency": 0.5490552186965942
        },
        {
          "action_code": "R23.05",
          "frequency": 0.0005732597201131284
        },
        {
          "action_code": "R45.35",
          "frequency": 0
        },
        {
          "action_code": "RAI",
          "frequency": 0
        }
      ]
    },
    {
      "name": "Qh",
      "solutions": [
        {
          "action_code": "X",
          "frequency": 0.835970938205719
        },
        {
          "action_code": "R11.5",
          "frequency": 0.11079587787389755
        },
        {
          "action_code": "R23.05",
          "frequency": 0.05323316156864166
        },
        {
          "action_code": "R45.35",
          "frequency": 0
        },
        {
          "action_code": "RAI",
          "frequency": 0
        }
      ]
    },
    {
      "name": "Qs",
      "solutions": [
        {
          "action_code": "X",
          "frequency": 0.45037153363227844
        },
        {
          "action_code": "R11.5",
          "frequency": 0.5490552186965942
        },
        {
          "action_code": "R23.05",
          "frequency": 0.0005732597201131284
        },
        {
          "action_code": "R45.35",
          "frequency": 0
        },
        {
          "action_code": "RAI",
          "frequency": 0
        }
      ]
    },
    {
      "name": "Kc",
      "solutions": [
        {
          "action_code": "X",
          "frequency": 0.5167016386985779
        },
        {
          "action_code": "R11.5",
          "frequency": 0.42373955249786377
        },
        {
          "action_code": "R23.05",
          "frequency": 0.05955824628472328
        },
        {
          "action_code": "R45.35",
          "frequency": 5.765599553342327e-7
        },
        {
          "action_code": "RAI",
          "frequency": 0
        }
      ]
    },
    {
      "name": "Kd",
      "solutions": [
        {
          "action_code": "X",
          "frequency": 0.5167016386985779
        },
        {
          "action_code": "R11.5",
          "frequency": 0.42373955249786377
        },
        {
          "action_code": "R23.05",
          "frequency": 0.05955824628472328
        },
        {
          "action_code": "R45.35",
          "frequency": 5.765599553342327e-7
        },
        {
          "action_code": "RAI",
          "frequency": 0
        }
      ]
    },
    {
      "name": "Ks",
      "solutions": [
        {
          "action_code": "X",
          "frequency": 0.5167016386985779
        },
        {
          "action_code": "R11.5",
          "frequency": 0.42373955249786377
        },
        {
          "action_code": "R23.05",
          "frequency": 0.05955824628472328
        },
        {
          "action_code": "R45.35",
          "frequency": 5.765599553342327e-7
        },
        {
          "action_code": "RAI",
          "frequency": 0
        }
      ]
    },
    {
      "name": "Ac",
      "solutions": [
        {
          "action_code": "X",
          "frequency": 0.42500606179237366
        },
        {
          "action_code": "R11.5",
          "frequency": 0.5625753402709961
        },
        {
          "action_code": "R23.05",
          "frequency": 0.012418640777468681
        },
        {
          "action_code": "R45.35",
          "frequency": 0
        },
        {
          "action_code": "RAI",
          "frequency": 0
        }
      ]
    },
    {
      "name": "Ad",
      "solutions": [
        {
          "action_code": "X",
          "frequency": 0.42500606179237366
        },
        {
          "action_code": "R11.5",
          "frequency": 0.5625753402709961
        },
        {
          "action_code": "R23.05",
          "frequency": 0.012418640777468681
        },
        {
          "action_code": "R45.35",
          "frequency": 0
        },
        {
          "action_code": "RAI",
          "frequency": 0
        }
      ]
    },
    {
      "name": "Ah",
      "solutions": [
        {
          "action_code": "X",
          "frequency": 1
        },
        {
          "action_code": "R11.5",
          "frequency": 0
        },
        {
          "action_code": "R23.05",
          "frequency": 0
        },
        {
          "action_code": "R45.35",
          "frequency": 0
        },
        {
          "action_code": "RAI",
          "frequency": 0
        }
      ]
    },
    {
      "name": "As",
      "solutions": [
        {
          "action_code": "X",
          "frequency": 0.42500606179237366
        },
        {
          "action_code": "R11.5",
          "frequency": 0.5625753402709961
        },
        {
          "action_code": "R23.05",
          "frequency": 0.012418640777468681
        },
        {
          "action_code": "R45.35",
          "frequency": 0
        },
        {
          "action_code": "RAI",
          "frequency": 0
        }
      ]
    }
  ],
  "player_solutions": [
    {
      "position": "SB",
      "is_hero": true,
      "relative_position": "OOP",
      "solutions": [
        {
          "name": "2c",
          "ev": 16.228051852628216,
          "eq": 0.492364278,
          "eqr": 0.9443966182719191
        },
        {
          "name": "2d",
          "ev": 16.228051852628216,
          "eq": 0.492364278,
          "eqr": 0.9443966182719191
        },
        {
          "name": "2h",
          "ev": 17.226064753407645,
          "eq": 0.487081615,
          "eqr": 1.0133486916553343
        },
        {
          "name": "2s",
          "ev": 16.22805185262822,
          "eq": 0.492364278,
          "eqr": 0.9443966182719193
        },
        {
          "name": "3c",
          "ev": 16.32473804568784,
          "eq": 0.494565545,
          "eqr": 0.9457948331716601
        },
        {
          "name": "3d",
          "ev": 16.32473804568784,
          "eq": 0.494565545,
          "eqr": 0.9457948331716601
        },
        {
          "name": "3h",
          "ev": 17.439624593047462,
          "eq": 0.490107368,
          "eqr": 1.0195780415251912
        },
        {
          "name": "3s",
          "ev": 16.324738045687837,
          "eq": 0.494565545,
          "eqr": 0.9457948331716599
        },
        {
          "name": "4c",
          "ev": 16.262537761146664,
          "eq": 0.494565031,
          "eqr": 0.9421921583769713
        },
        {
          "name": "4d",
          "ev": 16.262537761146664,
          "eq": 0.494565031,
          "eqr": 0.9421921583769713
        },
        {
          "name": "4h",
          "ev": 17.330112242395675,
          "eq": 0.491256216,
          "eqr": 1.0108061832626591
        },
        {
          "name": "4s",
          "ev": 16.262537761146664,
          "eq": 0.494565031,
          "eqr": 0.9421921583769713
        },
        {
          "name": "5c",
          "ev": 16.537364862986223,
          "eq": 0.500027466,
          "eqr": 0.9476479359517899
        },
        {
          "name": "5d",
          "ev": 16.537364862986223,
          "eq": 0.500027466,
          "eqr": 0.9476479359517899
        },
        {
          "name": "5h",
          "ev": 17.390690080460487,
          "eq": 0.494292159,
          "eqr": 1.008109407156023
        },
        {
          "name": "5s",
          "ev": 16.537364862986227,
          "eq": 0.500027466,
          "eqr": 0.9476479359517901
        },
        {
          "name": "6c",
          "ev": 16.38959655125634,
          "eq": 0.497750337,
          "eqr": 0.9434769042203628
        },
        {
          "name": "6d",
          "ev": 16.389596551256343,
          "eq": 0.497750337,
          "eqr": 0.943476904220363
        },
        {
          "name": "6h",
          "ev": 17.494615812751636,
          "eq": 0.494186027,
          "eqr": 1.014351605797608
        },
        {
          "name": "6s",
          "ev": 16.389596551256343,
          "eq": 0.497750337,
          "eqr": 0.943476904220363
        },
        {
          "name": "7c",
          "ev": 16.23558703988686,
          "eq": 0.496346439,
          "eqr": 0.937254769033346
        },
        {
          "name": "7d",
          "ev": 16.23558703988686,
          "eq": 0.496346439,
          "eqr": 0.937254769033346
        },
        {
          "name": "7h",
          "ev": 17.26527661702725,
          "eq": 0.488673976,
          "eqr": 1.0123458393259428
        },
        {
          "name": "7s",
          "ev": 16.235587039886855,
          "eq": 0.496346439,
          "eqr": 0.9372547690333458
        },
        {
          "name": "8c",
          "ev": 16.548296719396003,
          "eq": 0.500075071,
          "eqr": 0.948184097307503
        },
        {
          "name": "8d",
          "ev": 16.548296719396003,
          "eq": 0.500075071,
          "eqr": 0.948184097307503
        },
        {
          "name": "8s",
          "ev": 16.548296719396003,
          "eq": 0.500075071,
          "eqr": 0.948184097307503
        },
        {
          "name": "9c",
          "ev": 15.409283632990114,
          "eq": 0.483994801,
          "eqr": 0.9122551538763489
        },
        {
          "name": "9d",
          "ev": 15.409283632990114,
          "eq": 0.483994801,
          "eqr": 0.9122551538763489
        },
        {
          "name": "9h",
          "ev": 17.100432882704418,
          "eq": 0.482442649,
          "eqr": 1.0156310832725675
        },
        {
          "name": "9s",
          "ev": 15.40928363299011,
          "eq": 0.483994801,
          "eqr": 0.9122551538763487
        },
        {
          "name": "Tc",
          "ev": 17.855364169320584,
          "eq": 0.549585837,
          "eqr": 0.9309101231046466
        },
        {
          "name": "Td",
          "ev": 17.855364169320577,
          "eq": 0.549585837,
          "eqr": 0.9309101231046463
        },
        {
          "name": "Th",
          "ev": 17.367650740971623,
          "eq": 0.505315417,
          "eqr": 0.9848114774171047
        },
        {
          "name": "Ts",
          "ev": 17.855364169320577,
          "eq": 0.549585837,
          "eqr": 0.9309101231046463
        },
        {
          "name": "Jc",
          "ev": 16.83744514765452,
          "eq": 0.496008276,
          "eqr": 0.9726617646861215
        },
        {
          "name": "Jd",
          "ev": 16.83744514765452,
          "eq": 0.496008276,
          "eqr": 0.9726617646861215
        },
        {
          "name": "Js",
          "ev": 16.83744514765452,
          "eq": 0.496008276,
          "eqr": 0.9726617646861215
        },
        {
          "name": "Qc",
          "ev": 17.769871026440097,
          "eq": 0.546978465,
          "eqr": 0.9308691136931415
        },
        {
          "name": "Qd",
          "ev": 17.769871026440093,
          "eq": 0.546978465,
          "eqr": 0.9308691136931413
        },
        {
          "name": "Qh",
          "ev": 16.39927577815594,
          "eq": 0.485858861,
          "eqr": 0.9671394853337388
        },
        {
          "name": "Qs",
          "ev": 17.769871026440093,
          "eq": 0.546978465,
          "eqr": 0.9308691136931413
        },
        {
          "name": "Kc",
          "ev": 17.644205366542316,
          "eq": 0.503277459,
          "eqr": 1.0045445402774555
        },
        {
          "name": "Kd",
          "ev": 17.644205366542312,
          "eq": 0.503277459,
          "eqr": 1.0045445402774553
        },
        {
          "name": "Ks",
          "ev": 17.644205366542316,
          "eq": 0.503277459,
          "eqr": 1.0045445402774555
        },
        {
          "name": "Ac",
          "ev": 18.25304153039408,
          "eq": 0.551644136,
          "eqr": 0.9480927138345889
        },
        {
          "name": "Ad",
          "ev": 18.253041530394082,
          "eq": 0.551644136,
          "eqr": 0.9480927138345892
        },
        {
          "name": "Ah",
          "ev": 15.085056236600487,
          "eq": 0.475091779,
          "eqr": 0.9097959331011033
        },
        {
          "name": "As",
          "ev": 18.253041530394086,
          "eq": 0.551644136,
          "eqr": 0.9480927138345893
        }
      ],
      "total_ev": 16.83642756850025,
      "total_eq": 0.5044052140816324,
      "total_eqr": 0.9567502025564253
    },
    {
      "position": "BTN",
      "is_hero": false,
      "relative_position": "IP",
      "solutions": [
        {
          "name": "2c",
          "ev": 18.073130308258587,
          "eq": 0.507635739,
          "eqr": 1.0201305716702513
        },
        {
          "name": "2d",
          "ev": 18.073130308258587,
          "eq": 0.507635739,
          "eqr": 1.0201305716702513
        },
        {
          "name": "2h",
          "ev": 17.07543282841884,
          "eq": 0.512918351,
          "eqr": 0.9538894744810422
        },
        {
          "name": "2s",
          "ev": 18.073130308258587,
          "eq": 0.507635739,
          "eqr": 1.0201305716702513
        },
        {
          "name": "3c",
          "ev": 17.976039299406164,
          "eq": 0.505434495,
          "eqr": 1.0190692649406636
        },
        {
          "name": "3d",
          "ev": 17.976039299406164,
          "eq": 0.505434495,
          "eqr": 1.0190692649406636
        },
        {
          "name": "3h",
          "ev": 16.86185869466167,
          "eq": 0.509892553,
          "eqr": 0.9475482839629175
        },
        {
          "name": "3s",
          "ev": 17.976039299406164,
          "eq": 0.505434495,
          "eqr": 1.0190692649406636
        },
        {
          "name": "4c",
          "ev": 18.038354812333626,
          "eq": 0.505434997,
          "eqr": 1.0226009420521533
        },
        {
          "name": "4d",
          "ev": 18.038354812333626,
          "eq": 0.505434997,
          "eqr": 1.0226009420521533
        },
        {
          "name": "4h",
          "ev": 16.970262124692887,
          "eq": 0.508743702,
          "eqr": 0.9557935108831969
        },
        {
          "name": "4s",
          "ev": 18.038354812333626,
          "eq": 0.505434997,
          "eqr": 1.0226009420521533
        },
        {
          "name": "5c",
          "ev": 17.7630186200821,
          "eq": 0.499972586,
          "eqr": 1.0179938443706311
        },
        {
          "name": "5d",
          "ev": 17.7630186200821,
          "eq": 0.499972586,
          "eqr": 1.0179938443706311
        },
        {
          "name": "5h",
          "ev": 16.91168073755077,
          "eq": 0.505707786,
          "eqr": 0.9582122180326665
        },
        {
          "name": "5s",
          "ev": 17.7630186200821,
          "eq": 0.499972586,
          "eqr": 1.0179938443706311
        },
        {
          "name": "6c",
          "ev": 17.912139738785097,
          "eq": 0.502249704,
          "eqr": 1.0218857716364538
        },
        {
          "name": "6d",
          "ev": 17.912139738785097,
          "eq": 0.502249704,
          "eqr": 1.0218857716364538
        },
        {
          "name": "6h",
          "ev": 16.806264930787854,
          "eq": 0.505813903,
          "eqr": 0.952039606307571
        },
        {
          "name": "6s",
          "ev": 17.9121397387851,
          "eq": 0.502249704,
          "eqr": 1.021885771636454
        },
        {
          "name": "7c",
          "ev": 18.065514865592178,
          "eq": 0.503653516,
          "eqr": 1.0277631599022976
        },
        {
          "name": "7d",
          "ev": 18.065514865592178,
          "eq": 0.503653516,
          "eqr": 1.0277631599022976
        },
        {
          "name": "7h",
          "ev": 17.036659428907647,
          "eq": 0.511325947,
          "eqr": 0.9546873838337141
        },
        {
          "name": "7s",
          "ev": 18.065514865592174,
          "eq": 0.503653516,
          "eqr": 1.0277631599022974
        },
        {
          "name": "8c",
          "ev": 17.75235341003277,
          "eq": 0.499925001,
          "eqr": 1.017479462866292
        },
        {
          "name": "8d",
          "ev": 17.75235341003277,
          "eq": 0.499925001,
          "eqr": 1.017479462866292
        },
        {
          "name": "8s",
          "ev": 17.752353410032768,
          "eq": 0.499925001,
          "eqr": 1.0174794628662918
        },
        {
          "name": "9c",
          "ev": 18.891654081850977,
          "eq": 0.516005245,
          "eqr": 1.0490361195478097
        },
        {
          "name": "9d",
          "ev": 18.891654081850977,
          "eq": 0.516005245,
          "eqr": 1.0490361195478097
        },
        {
          "name": "9h",
          "ev": 17.200596274297585,
          "eq": 0.517557346,
          "eqr": 0.9522688939694646
        },
        {
          "name": "9s",
          "ev": 18.891654081850977,
          "eq": 0.516005245,
          "eqr": 1.0490361195478097
        },
        {
          "name": "Tc",
          "ev": 16.44504074456486,
          "eq": 0.450414178,
          "eqr": 1.0461584667555854
        },
        {
          "name": "Td",
          "ev": 16.44504074456486,
          "eq": 0.450414178,
          "eqr": 1.0461584667555854
        },
        {
          "name": "Th",
          "ev": 16.932938765727474,
          "eq": 0.494684563,
          "eqr": 0.9807956992073258
        },
        {
          "name": "Ts",
          "ev": 16.445040744564864,
          "eq": 0.450414178,
          "eqr": 1.0461584667555857
        },
        {
          "name": "Jc",
          "ev": 17.463470690454706,
          "eq": 0.50399174,
          "eqr": 0.9928455963766178
        },
        {
          "name": "Jd",
          "ev": 17.46347069045471,
          "eq": 0.50399174,
          "eqr": 0.9928455963766181
        },
        {
          "name": "Js",
          "ev": 17.46347069045471,
          "eq": 0.503991739,
          "eqr": 0.9928455983465819
        },
        {
          "name": "Qc",
          "ev": 16.532708725530448,
          "eq": 0.453021559,
          "eqr": 1.0456822042622094
        },
        {
          "name": "Qd",
          "ev": 16.53270872553045,
          "eq": 0.453021559,
          "eqr": 1.0456822042622096
        },
        {
          "name": "Qh",
          "ev": 17.901328901369684,
          "eq": 0.514141087,
          "eqr": 0.9976484532759502
        },
        {
          "name": "Qs",
          "ev": 16.53270872553045,
          "eq": 0.453021559,
          "eqr": 1.0456822042622096
        },
        {
          "name": "Kc",
          "ev": 16.6563136247675,
          "eq": 0.4967225,
          "eqr": 0.9608146803308582
        },
        {
          "name": "Kd",
          "ev": 16.656313624767495,
          "eq": 0.4967225,
          "eqr": 0.9608146803308579
        },
        {
          "name": "Ks",
          "ev": 16.656313624767495,
          "eq": 0.496722498,
          "eqr": 0.9608146841994754
        },
        {
          "name": "Ac",
          "ev": 16.048721445170795,
          "eq": 0.4483559,
          "eqr": 1.0256333239076916
        },
        {
          "name": "Ad",
          "ev": 16.04872144517079,
          "eq": 0.4483559,
          "eqr": 1.0256333239076914
        },
        {
          "name": "Ah",
          "ev": 19.213981479805888,
          "eq": 0.524908197,
          "eqr": 1.0488384161066209
        },
        {
          "name": "As",
          "ev": 16.048721445170795,
          "eq": 0.4483559,
          "eqr": 1.0256333239076916
        }
      ],
      "total_ev": 17.464620107483874,
      "total_eq": 0.4955947941224489,
      "total_eqr": 1.0102653504440324
    }
  ],
  "totals": [
    {
      "action_code": "X",
      "frequency": 0.5682318107205995
    },
    {
      "action_code": "R11.5",
      "frequency": 0.3726199064023641
    },
    {
      "action_code": "R23.05",
      "frequency": 0.05914825037577931
    },
    {
      "action_code": "R45.35",
      "frequency": 3.5299589102095875e-8
    },
    {
      "action_code": "RAI",
      "frequency": 0
    }
  ],
  "game_point": {
    "game": {
      "players": [
        {
          "position": "UTG",
          "relative_postflop_position": null,
          "hand": null,
          "is_dealer": false,
          "is_folded": true,
          "is_hero": false,
          "is_active": false,
          "stack": "100.000",
          "current_stack": "100.000",
          "chips_on_table": "0.00",
          "bounty": null,
          "chips_by_denomination": []
        },
        {
          "position": "HJ",
          "relative_postflop_position": null,
          "hand": null,
          "is_dealer": false,
          "is_folded": true,
          "is_hero": false,
          "is_active": false,
          "stack": "100.000",
          "current_stack": "100.000",
          "chips_on_table": "0.00",
          "bounty": null,
          "chips_by_denomination": []
        },
        {
          "position": "CO",
          "relative_postflop_position": null,
          "hand": null,
          "is_dealer": false,
          "is_folded": true,
          "is_hero": false,
          "is_active": false,
          "stack": "100.000",
          "current_stack": "100.000",
          "chips_on_table": "0.00",
          "bounty": null,
          "chips_by_denomination": []
        },
        {
          "position": "BTN",
          "relative_postflop_position": "IP",
          "hand": null,
          "is_dealer": true,
          "is_folded": false,
          "is_hero": false,
          "is_active": false,
          "stack": "100.000",
          "current_stack": "83.050",
          "chips_on_table": "0.00",
          "bounty": null,
          "chips_by_denomination": []
        },
        {
          "position": "SB",
          "relative_postflop_position": "OOP",
          "hand": null,
          "is_dealer": false,
          "is_folded": false,
          "is_hero": false,
          "is_active": true,
          "stack": "100.000",
          "current_stack": "83.050",
          "chips_on_table": "0.00",
          "bounty": null,
          "chips_by_denomination": []
        },
        {
          "position": "BB",
          "relative_postflop_position": null,
          "hand": null,
          "is_dealer": false,
          "is_folded": true,
          "is_hero": false,
          "is_active": false,
          "stack": "100.000",
          "current_stack": "99.000",
          "chips_on_table": "0.00",
          "bounty": null,
          "chips_by_denomination": []
        }
      ],
      "current_street": {
        "type": "TURN",
        "start_pot": "34.900",
        "start_pot_by_denomination": [
          {
            "denomination": "25.0",
            "amount": 1
          },
          {
            "denomination": "5.0",
            "amount": 2
          }
        ],
        "end_pot": "34.900",
        "end_pot_by_denomination": [
          {
            "denomination": "25.0",
            "amount": 1
          },
          {
            "denomination": "5.0",
            "amount": 2
          }
        ]
      },
      "pot": "34.900",
      "pot_by_denomination": [
        {
          "denomination": "25.0",
          "amount": 1
        },
        {
          "denomination": "5.0",
          "amount": 2
        }
      ],
      "pot_odds": null,
      "active_position": "SB",
      "board": "KhJh8h",
      "bet_display_name": "BET"
    },
    "available_actions": [
      {
        "action": {
          "code": "X",
          "position": "SB",
          "type": "CHECK",
          "betsize": "0.000",
          "allin": false,
          "is_hand_end": false,
          "is_showdown": false,
          "next_street": false,
          "display_name": "CHECK",
          "simple_group": "CHECK",
          "advanced_group": "CHECK",
          "betsize_by_pot": null,
          "next_position": "BTN"
        },
        "frequency": null,
        "is_solution_end": false,
        "can_be_solved_by_ai": false,
        "next_position": "BTN",
        "selected": false
      },
      {
        "action": {
          "code": "R11.5",
          "position": "SB",
          "type": "RAISE",
          "betsize": "11.500",
          "allin": false,
          "is_hand_end": false,
          "is_showdown": false,
          "next_street": false,
          "display_name": "BET",
          "simple_group": "RAISE",
          "advanced_group": "BET_SMALL",
          "betsize_by_pot": "0.32951289",
          "next_position": "BTN"
        },
        "frequency": null,
        "is_solution_end": false,
        "can_be_solved_by_ai": false,
        "next_position": "BTN",
        "selected": false
      },
      {
        "action": {
          "code": "R23.05",
          "position": "SB",
          "type": "RAISE",
          "betsize": "23.050",
          "allin": false,
          "is_hand_end": false,
          "is_showdown": false,
          "next_street": false,
          "display_name": "BET",
          "simple_group": "RAISE",
          "advanced_group": "BET_MEDIUM",
          "betsize_by_pot": "0.66045845",
          "next_position": "BTN"
        },
        "frequency": null,
        "is_solution_end": false,
        "can_be_solved_by_ai": false,
        "next_position": "BTN",
        "selected": false
      },
      {
        "action": {
          "code": "R45.35",
          "position": "SB",
          "type": "RAISE",
          "betsize": "45.350",
          "allin": false,
          "is_hand_end": false,
          "is_showdown": false,
          "next_street": false,
          "display_name": "BET",
          "simple_group": "RAISE",
          "advanced_group": "BET_OVERBET",
          "betsize_by_pot": "1.29942693",
          "next_position": "BTN"
        },
        "frequency": null,
        "is_solution_end": false,
        "can_be_solved_by_ai": false,
        "next_position": "BTN",
        "selected": false
      },
      {
        "action": {
          "code": "RAI",
          "position": "SB",
          "type": "RAISE",
          "betsize": "83.050",
          "allin": true,
          "is_hand_end": false,
          "is_showdown": false,
          "next_street": false,
          "display_name": "ALLIN",
          "simple_group": "RAISE",
          "advanced_group": "BET_OVERBET",
          "betsize_by_pot": "2.37965616",
          "next_position": "BTN"
        },
        "frequency": null,
        "is_solution_end": false,
        "can_be_solved_by_ai": false,
        "next_position": "BTN",
        "selected": false
      }
    ],
    "custom_solution_id": null,
    "is_node_locked": false,
    "is_edited": false,
    "forced_fold": false,
    "available_node_edits": null,
    "merged_actions": [],
    "preset_action_code": "X"
  }
}